printPersian/__init__.py
printPersian/convertPersian.py
printPersian-0.0.1.dist-info/METADATA
printPersian-0.0.1.dist-info/WHEEL
printPersian-0.0.1.dist-info/top_level.txt
printPersian-0.0.1.dist-info/RECORD
