Metadata-Version: 2.1
Name: printPersian
Version: 0.0.1
Summary: print persian
Author: omidhosseini
Author-email: omid.iipa75@gmail.com
License: UNKNOWN
Keywords: python,print,persian,vs code,console
Platform: UNKNOWN
Classifier: Development Status :: 1 - Planning
Classifier: Intended Audience :: Developers
Classifier: Programming Language :: Python :: 3
Classifier: Operating System :: Unix
Classifier: Operating System :: MacOS :: MacOS X
Classifier: Operating System :: Microsoft :: Windows
Requires-Dist: arabic-reshaper (==2.1.3)
Requires-Dist: python-bidi (==0.4.2)
Requires-Dist: setuptools (==62.1.0)
